Learn_ver/ex3_alu/ex3_test/tb_seg/seg.v
module seg(i_signbit, seg_in, seg_out);
    input i_signbit;            // 控制是否输出符号位
    input [3:0] seg_in;         // 4位的输入
    output reg [7:0] seg_out;   // 8位输出，对数码管的控制信号

    // 参数定义：数码管显示编码
    parameter seg0 = 8'b11111101; // 数字 0
    parameter seg1 = 8'b01100000; // 数字 1
    parameter seg2 = 8'b11011010; // 数字 2
    parameter seg3 = 8'b11110010; // 数字 3
    parameter seg4 = 8'b01100110; // 数字 4
    parameter seg5 = 8'b10110110; // 数字 5
    parameter seg6 = 8'b10111110; // 数字 6
    parameter seg7 = 8'b11100000; // 数字 7
    parameter seg8 = 8'b11111111; // 数字 8

    always @(*) begin
        // 当收到i_signbit = 0,无符号数显示 (0 到 7)
        if (~i_signbit) begin
            case (seg_in)
                4'd0:  seg_out = ~seg0;
                4'd1:  seg_out = ~seg1;
                4'd2:  seg_out = ~seg2;
                4'd3:  seg_out = ~seg3;
                4'd4:  seg_out = ~seg4;
                4'd5:  seg_out = ~seg5;
                4'd6:  seg_out = ~seg6;
                4'd7:  seg_out = ~seg7;
                4'd8:  seg_out = ~seg8;
                default: seg_out = 8'b00000000; // 默认熄灭
            endcase
        end
        // 有符号数显示 (-1 到 -8)
        else begin
            case (seg_in)
                4'd1:  seg_out = ~seg1; // 显示 -1
                4'd2:  seg_out = ~seg2; // 显示 -2
                4'd3:  seg_out = ~seg3; // 显示 -3
                4'd4:  seg_out = ~seg4; // 显示 -4
                4'd5:  seg_out = ~seg5; // 显示 -5
                4'd6:  seg_out = ~seg6; // 显示 -6
                4'd7:  seg_out = ~seg7; // 显示 -7
                4'd8:  seg_out = ~seg8; // 显示 -8
                default: seg_out = 8'b00000000; // 默认熄灭
            endcase
        end
    end
endmodule

Learn_ver/ex3_alu/ex3_test/tb_seg/tb_seg.v
module tb_seg;
    //接口
    reg i_signbit;
    reg [3:0] seg_in;
    wire [7:0] seg_out;


    //实例化被测模块
    seg uut(
        .i_signbit(i_signbit),
        .seg_in(seg_in),
        .seg_out(seg_out)
    );

    //时钟信号生成
    // initial begin
    //     clk = 0;
    //     forever #5 clk = ~clk;
    // end

    //激励信号
    initial begin
        //生成VCD波形文件
        $dumpfile("tb_seg.vcd");
        $dumpvars(0, tb_seg);

        
        i_signbit = 0;
        seg_in = 4'd0;
        #10 seg_in = 4'd1;
        #10 seg_in = 4'd2;
        #10 seg_in = 4'd3;
        #10 seg_in = 4'd4;
        #10 seg_in = 4'd5;
        #10 seg_in = 4'd6;
        #10 seg_in = 4'd7;
        #10 seg_in = 4'd8;

        //切换到有符号
        i_signbit = 1;
        #10 seg_in = 4'd1;
        #10 seg_in = 4'd2;
        #10 seg_in = 4'd3;
        #10 seg_in = 4'd4;
        #10 seg_in = 4'd5;
        #10 seg_in = 4'd6;
        #10 seg_in = 4'd7;
        #10 seg_in = 4'd8;

        //结束仿真
        #10 $finish;
    end
        //输出监视
        initial begin
            $monitor("时间%t: i_signbit = %b, seg_in = %d, seg_out = %b",
                        $time, i_signbit, seg_in, seg_out);
        end


    

endmodule

Learn_ver/ex3_alu/ex3_test/tb_seg/tb_seg.vcd
$date
	Wed Dec  4 11:40:15 2024
$end
$version
	Icarus Verilog
$end
$timescale
	1s
$end
$scope module tb_seg $end
$var wire 8 ! seg_out [7:0] $end
$var reg 1 " i_signbit $end
$var reg 4 # seg_in [3:0] $end
$scope module uut $end
$var wire 1 " i_signbit $end
$var wire 4 $ seg_in [3:0] $end
$var reg 8 % seg_out [7:0] $end
$upscope $end
$upscope $end
$enddefinitions $end
#0
$dumpvars
b10 %
b0 $
b0 #
0"
b10 !
$end
#10
b10011111 !
b10011111 %
b1 #
b1 $
#20
b100101 !
b100101 %
b10 #
b10 $
#30
b1101 !
b1101 %
b11 #
b11 $
#40
b10011001 !
b10011001 %
b100 #
b100 $
#50
b1001001 !
b1001001 %
b101 #
b101 $
#60
b1000001 !
b1000001 %
b110 #
b110 $
#70
b11111 !
b11111 %
b111 #
b111 $
#80
b0 !
b0 %
1"
b1000 #
b1000 $
#90
b10011111 !
b10011111 %
b1 #
b1 $
#100
b100101 !
b100101 %
b10 #
b10 $
#110
b1101 !
b1101 %
b11 #
b11 $
#120
b10011001 !
b10011001 %
b100 #
b100 $
#130
b1001001 !
b1001001 %
b101 #
b101 $
#140
b1000001 !
b1000001 %
b110 #
b110 $
#150
b11111 !
b11111 %
b111 #
b111 $
#160
b0 !
b0 %
b1000 #
b1000 $
