Learn_ver/ex9/ex9_test/char_display/char_display.v
module char_display(
    input clk,                  // 时钟信号
    input clrn,                 // 复位信号
    input [7:0] ascii,          // 输入的ascii码，选择需要显示的字符
    input [9:0] x,              // 显示字符的横坐标
    input [9:0] y,              // 显示字符的纵坐标
    output reg [23:0] vga_data  // vga输出数据，rgb的颜色值
);

    // 字符点阵（暂时只支持 ABCD 四个字符）
    // 每个字符由7x7的点阵表示
    reg [6:0] font_A [0:6];
    reg [6:0] font_B [0:6];
    reg [6:0] font_C [0:6];
    reg [6:0] font_D [0:6];

    // 当前的字符点阵，大小为7x7
    reg [6:0] current_font [0:6];

    // 使用initial块初始化字符点阵
    initial begin
        font_A[0] = 7'b0001110; 
        font_A[1] = 7'b0010001; 
        font_A[2] = 7'b0011111;
        font_A[3] = 7'b0010001; 
        font_A[4] = 7'b0010001; 
        font_A[5] = 7'b0000000;
        font_A[6] = 7'b0000000;

        font_B[0] = 7'b0011110; 
        font_B[1] = 7'b0010001; 
        font_B[2] = 7'b0011110;
        font_B[3] = 7'b0010001; 
        font_B[4] = 7'b0011110; 
        font_B[5] = 7'b0000000;
        font_B[6] = 7'b0000000;

        font_C[0] = 7'b0001111; 
        font_C[1] = 7'b0010000; 
        font_C[2] = 7'b0010000;
        font_C[3] = 7'b0010000; 
        font_C[4] = 7'b0001111; 
        font_C[5] = 7'b0000000;
        font_C[6] = 7'b0000000;

        font_D[0] = 7'b0011110; 
        font_D[1] = 7'b0010001; 
        font_D[2] = 7'b0010001;
        font_D[3] = 7'b0010001; 
        font_D[4] = 7'b0011110; 
        font_D[5] = 7'b0000000;
        font_D[6] = 7'b0000000;
    end

    // 根据输入的ascii码，选择相应的点阵
    always @(*) begin
        case (ascii)
            8'h41: begin
                current_font[0] = font_A[0];
                current_font[1] = font_A[1];
                current_font[2] = font_A[2];
                current_font[3] = font_A[3];
                current_font[4] = font_A[4];
                current_font[5] = font_A[5];
                current_font[6] = font_A[6];
            end
            8'h42: begin
                current_font[0] = font_B[0];
                current_font[1] = font_B[1];
                current_font[2] = font_B[2];
                current_font[3] = font_B[3];
                current_font[4] = font_B[4];
                current_font[5] = font_B[5];
                current_font[6] = font_B[6];
            end
            8'h43: begin
                current_font[0] = font_C[0];
                current_font[1] = font_C[1];
                current_font[2] = font_C[2];
                current_font[3] = font_C[3];
                current_font[4] = font_C[4];
                current_font[5] = font_C[5];
                current_font[6] = font_C[6];
            end
            8'h44: begin
                current_font[0] = font_D[0];
                current_font[1] = font_D[1];
                current_font[2] = font_D[2];
                current_font[3] = font_D[3];
                current_font[4] = font_D[4];
                current_font[5] = font_D[5];
                current_font[6] = font_D[6];
            end
            default: begin
                current_font[0] = 7'b0000000;
                current_font[1] = 7'b0000000;
                current_font[2] = 7'b0000000;
                current_font[3] = 7'b0000000;
                current_font[4] = 7'b0000000;
                current_font[5] = 7'b0000000;
                current_font[6] = 7'b0000000;
            end
        endcase
    end

    // 根据坐标和点阵值，生成vga输出数据
    always @(*) begin
        // 如果y小于7且当前点阵中该位置为1，则点亮该位置
        if (x < 7 && y < 7 && current_font[y][x]) 
            vga_data = 24'hFFFFFF;  // 点亮该位置（白色）
        else
            vga_data = 24'h000000;  // 否则黑色
    end

endmodule

Learn_ver/ex9/ex9_test/char_display/tb_char_display.v
`timescale 1ns / 1ps

module tb_char_display;
    //接口信号
    //输入信号
    reg clk;
    reg clrn;
    reg [7:0] ascii;
    reg [9:0] x;
    reg [9:0] y;

    //输出信号
    wire [23:0] vga_data;

    //实例化被测试模块
    char_display uut(
        .clk(clk),
        .clrn(clrn),
        .ascii(ascii),
        .x(x),
        .y(y),
        .vga_data(vga_data)
    );

    //生成时钟信号
    always begin
        #5 clk = ~clk;
    end

    //初始化信号
    initial begin
        //初始化信号
        clk = 0;
        clrn = 0;
        ascii = 8'h00;
        x = 0;
        y = 0;

        //等待一段时间后释放复位
        #20 clrn = 1;

        //测试字符A
        #10 ascii = 8'h41;
        #10 x = 0; y = 0;
        #10 x = 1; y = 0;
        #10 x = 2; y = 0;
        #10 x = 3; y = 0;
        #10 x = 4; y = 0;
        #10 x = 5; y = 0;
        #10 x = 6; y = 0;

        //测试字符B
        #20 ascii = 8'h42;
        #10 x = 0; y = 0;
        #10 x = 1; y = 0;
        #10 x = 2; y = 0;

        //测试字符C
        #20 ascii = 8'h43;
        #10 x = 0; y = 0;
        #10 x = 1; y = 0;

        //测试字符D
        #20 ascii = 8'h44;
        #10 x = 0; y = 0;
        #10 x = 1; y = 0;

        //结束仿真
        #100 $finish;
    end

    initial begin
        $monitor("Time: %t | ASCII: %h | x: %d , y: %d | VGA Data: %h",
                    $time, ascii , x, y, vga_data);
    end     

    initial begin
    $dumpfile("char_display.vcd");
    $dumpvars(0, tb_char_display);
end

endmodule

Learn_ver/ex9/ex9_test/char_display/char_display.vcd
$date
	Thu Dec  5 12:39:18 2024
$end
$version
	Icarus Verilog
$end
$timescale
	1ps
$end
$scope module tb_char_display $end
$var wire 24 ! vga_data [23:0] $end
$var reg 8 " ascii [7:0] $end
$var reg 1 # clk $end
$var reg 1 $ clrn $end
$var reg 10 % x [9:0] $end
$var reg 10 & y [9:0] $end
$scope module uut $end
$var wire 8 ' ascii [7:0] $end
$var wire 1 # clk $end
$var wire 1 $ clrn $end
$var wire 10 ( x [9:0] $end
$var wire 10 ) y [9:0] $end
$var reg 24 * vga_data [23:0] $end
$upscope $end
$upscope $end
$enddefinitions $end
#0
$dumpvars
b0 *
b0 )
b0 (
b0 '
b0 &
b0 %
0$
0#
b0 "
b0 !
$end
#5000
1#
#10000
0#
#15000
1#
#20000
0#
1$
#25000
1#
#30000
0#
b1000001 "
b1000001 '
#35000
1#
#40000
0#
#45000
1#
#50000
b111111111111111111111111 !
b111111111111111111111111 *
0#
b1 %
b1 (
#55000
1#
#60000
0#
b10 %
b10 (
#65000
1#
#70000
0#
b11 %
b11 (
#75000
1#
#80000
b0 !
b0 *
0#
b100 %
b100 (
#85000
1#
#90000
0#
b101 %
b101 (
#95000
1#
#100000
0#
b110 %
b110 (
#105000
1#
#110000
0#
#115000
1#
#120000
0#
b1000010 "
b1000010 '
#125000
1#
#130000
0#
b0 %
b0 (
#135000
1#
#140000
b111111111111111111111111 !
b111111111111111111111111 *
0#
b1 %
b1 (
#145000
1#
#150000
0#
b10 %
b10 (
#155000
1#
#160000
0#
#165000
1#
#170000
0#
b1000011 "
b1000011 '
#175000
1#
#180000
0#
b0 %
b0 (
#185000
1#
#190000
0#
b1 %
b1 (
#195000
1#
#200000
0#
#205000
1#
#210000
0#
b1000100 "
b1000100 '
#215000
1#
#220000
b0 !
b0 *
0#
b0 %
b0 (
#225000
1#
#230000
b111111111111111111111111 !
b111111111111111111111111 *
0#
b1 %
b1 (
