Learn_ver/ex6_reg/example/shift_reg8/reg_control.v
module reg_control(clk, reset, control, s_in, d_in, reg_out);
    input clk;                  //时钟信号
    input reset;                //复位信号
    input [2:0] control;        //控制信号，选择模式
    input s_in;                 //串行输入
    input [7:0] d_in;           //并行输入
    output reg [7:0] reg_out;   //并行输出

    always @(posedge clk or negedge reset) begin
        if(reset) begin
            reg_out <= 8'b0;
        end else begin
            case(control)
                3'b000: reg_out <= 8'b0;    //清零
                3'b001: reg_out <= d_in;    //置数
                3'b010: reg_out <= reg_out >> 1;    //逻辑右移
                3'b011: reg_out <= reg_out << 1;    //逻辑左移
                3'b100: reg_out <= {reg_out[7], reg_out[7:1]};  //算术右移
                3'b101: reg_out <= {reg_out[6:0], s_in};    //左端串行输入，右移
                3'b110: reg_out <= {reg_out[0], reg_out[7:1]};//循环右移
                3'b111: reg_out <= {reg_out[6:0], reg_out[7]};//循环左移
                default: reg_out <= reg_out;    //默认保持不变
            endcase
        end
    end
endmodule

Learn_ver/ex6_reg/example/shift_reg8/tb_reg_control.v
module tb_reg_control;

    reg clk;
    reg reset;
    reg [2:0] control;
    reg s_in;
    reg [7:0] d_in;
    wire [7:0] reg_out;

    //实例化
    reg_control uut(
        .clk(clk),
        .reset(reset),
        .control(control),
        .s_in(s_in),
        .d_in(d_in),
        .reg_out(reg_out)
    );

    // 波形生成
    initial begin
        $dumpfile("dump.vcd");  // 指定波形输出文件名
        $dumpvars(0, tb_reg_control);
    $display("Dumping waveforms to dump.vcd...");
    #1000; // 运行仿真指定时间后自动停止波形记录（可根据需要调整）
    $finish; // 结束仿真
    end

    //时钟信号生成
    initial begin
        clk = 0;
        forever #5 clk = ~clk;      //10ns 时钟周期
    end

    //测试逻辑
    initial begin
        //初始化
        reset = 0;
        control = 3'b000;
        s_in = 0;
        d_in = 8'b0;
        #15;

        //释放复位，测试清零
        reset = 1;
        #10 control = 3'b000;

        //测试置数
        #10 control = 3'b001; d_in = 8'b10101010;

        //测试逻辑右移
        control = 3'b010;
        #10;

        //测试逻辑左移
        control = 3'b011;
        #10;

        //测试算术右移
        control = 3'b100;
        #10;

        //测试左端串行输入并右移
        control = 3'b101; s_in = 1;
        #10 s_in = 0;
        #10;

        //测试循环右移
        control = 3'b110;
        #10;

        //测试循环左移
        control = 3'b111;
        #10;

        $finish;//结束仿真
    end
endmodule

Learn_ver/ex6_reg/example/shift_reg8/dump.vcd
$date
	Tue Nov 26 10:44:56 2024
$end
$version
	Icarus Verilog
$end
$timescale
	1s
$end
$scope module tb_reg_control $end
$var wire 8 ! reg_out [7:0] $end
$var reg 1 " clk $end
$var reg 3 # control [2:0] $end
$var reg 8 $ d_in [7:0] $end
$var reg 1 % reset $end
$var reg 1 & s_in $end
$scope module uut $end
$var wire 1 " clk $end
$var wire 3 ' control [2:0] $end
$var wire 8 ( d_in [7:0] $end
$var wire 1 % reset $end
$var wire 1 & s_in $end
$var reg 8 ) reg_out [7:0] $end
$upscope $end
$upscope $end
$enddefinitions $end
#0
$dumpvars
b0 )
b0 (
b0 '
0&
0%
b0 $
b0 #
0"
b0 !
$end
#5
1"
#10
0"
#15
1"
1%
#20
0"
#25
1"
#30
0"
#35
1"
b10101010 $
b10101010 (
b10 #
b10 '
#40
0"
#45
1"
b11 #
b11 '
#50
0"
#55
1"
b100 #
b100 '
#60
0"
#65
b1 !
b1 )
1"
1&
b101 #
b101 '
#70
0"
#75
b10 !
b10 )
1"
0&
#80
0"
#85
b1 !
b1 )
1"
b110 #
b110 '
#90
0"
#95
b10 !
b10 )
1"
b111 #
b111 '
#100
0"
#105
b100 !
b100 )
1"
