Learn_Chisel/NanjingExperiment/ex6ShiftReg/verilog/vsrc/Combinational.v
module Combinational(
  input        clock,
  input        reset,
  input  [3:0] io_in,
  output [7:0] io_seg
);
  wire [7:0] _GEN_0 = io_in == 4'h9 ? 8'h9 : 8'hff; // @[Combinational.scala 22:{36,45} 23:25]
  wire [7:0] _GEN_1 = io_in == 4'h8 ? 8'h1 : _GEN_0; // @[Combinational.scala 21:{36,45}]
  wire [7:0] _GEN_2 = io_in == 4'h7 ? 8'h1f : _GEN_1; // @[Combinational.scala 20:{36,45}]
  wire [7:0] _GEN_3 = io_in == 4'h6 ? 8'h41 : _GEN_2; // @[Combinational.scala 19:{36,45}]
  wire [7:0] _GEN_4 = io_in == 4'h5 ? 8'h49 : _GEN_3; // @[Combinational.scala 18:{36,45}]
  wire [7:0] _GEN_5 = io_in == 4'h4 ? 8'h99 : _GEN_4; // @[Combinational.scala 17:{36,45}]
  wire [7:0] _GEN_6 = io_in == 4'h3 ? 8'hd : _GEN_5; // @[Combinational.scala 16:{36,45}]
  wire [7:0] _GEN_7 = io_in == 4'h2 ? 8'h25 : _GEN_6; // @[Combinational.scala 15:{36,45}]
  wire [7:0] _GEN_8 = io_in == 4'h1 ? 8'h9f : _GEN_7; // @[Combinational.scala 14:{36,45}]
  assign io_seg = io_in == 4'h0 ? 8'h3 : _GEN_8; // @[Combinational.scala 13:{29,38}]
endmodule

Learn_Chisel/NanjingExperiment/ex7FSM/test_run_dir/Combinational_should_pass/Combinational.vcd
$date
2025-01-09T07:47+0000
$end
$version
0.2
$end
$comment

$end
$timescale 1ns  $end
$scope module Combinational $end
 $var wire 1 ! clock $end
 $var wire 4 " io_in $end
 $var wire 1 # reset $end
 $var wire 8 $ io_seg $end
$upscope $end
$enddefinitions $end
$dumpvars
0#
b0000 "
0!
b00000000 $
$end
#0
1#
b00000011 $
#1
1!
#6
0!
0#
#11
1!
#16
0!
b0101 "
b01001001 $
#21
1!
#26
0!
b0001 "
b10011111 $
#31
1!
#36
0!
b0110 "
b01000001 $
#41
1!
#46
0!
b1001 "
b00001001 $
#51
1!
#56
0!
b0010 "
b00100101 $
#61
1!
#66
0!
b0111 "
b00011111 $
#71
1!
#76
0!
b0011 "
b00001101 $
#81
1!
#86
0!
b1000 "
b00000001 $
#91
1!
#96
0!
b0100 "
b10011001 $
#101
1!
#106
0!
b1010 "
b11111111 $
#111
1!
#116
0!
b0000 "
