Learn_ver/ex2_encode/示例/decode38.v
module decode38(x, en, y);
    input [2:0] x;
    input en;
    output reg [7:0] y;
    integer i;  //有符号整数变量，32位宽，用于描述循环变量和计算

    always @(x or en)
        if(en)
        begin
            for(i = 0; i <= 7; i = i+1)
                if({29'b0,x} == i)
                    y[i] = 1;
                else
                    y[i] = 0;
        end
        else
        y = 8'b00000000;
endmodule

Learn_ver/ex2_encode/示例/dump38.vcd
$version Generated by VerilatedVcd $end
$timescale 1s $end

 $scope module TOP $end
  $var wire  1 $ en $end
  $var wire  3 # x [2:0] $end
  $var wire  8 % y [7:0] $end
  $scope module decode38 $end
   $var wire  1 $ en $end
   $var wire 32 & i [31:0] $end
   $var wire  3 # x [2:0] $end
   $var wire  8 % y [7:0] $end
  $upscope $end
 $upscope $end
$enddefinitions $end


#1
b000 #
0$
b00000000 %
b00000000000000000000000000000000 &
#2
b001 #
#3
b010 #
#4
b011 #
#5
b100 #
#6
b101 #
#7
b110 #
#8
b111 #
#9
b000 #
1$
b00000001 %
b00000000000000000000000000001000 &
#10
b001 #
b00000010 %
#11
b010 #
b00000100 %
#12
b011 #
b00001000 %
#13
b100 #
b00010000 %
#14
b101 #
b00100000 %
#15
b110 #
b01000000 %
#16
b111 #
b10000000 %
