Learn_ver/ex2_encode/示例/encode42c.v
module encode42c(in_code, en, out_code);
    input [3:0] in_code;
    input en;
    output reg [1:0] out_code;

    always @(in_code or en) begin
        if(en) begin
            casez(in_code)
                4'b0001: out_code = 2'b00;
                4'b001z: out_code = 2'b01;
                4'b01zz: out_code = 2'b10;
                4'b1???: out_code = 2'b11;
                default: out_code = 2'b00;
            endcase    
        end else
            out_code = 2'b00;
    end


endmodule

Learn_ver/ex2_encode/示例/dump42c.vcd
$version Generated by VerilatedVcd $end
$timescale 1s $end

 $scope module TOP $end
  $var wire  1 $ en $end
  $var wire  4 # in_code [3:0] $end
  $var wire  2 % out_code [1:0] $end
  $scope module encode42c $end
   $var wire  1 $ en $end
   $var wire  4 # in_code [3:0] $end
   $var wire  2 % out_code [1:0] $end
  $upscope $end
 $upscope $end
$enddefinitions $end


#1
b0001 #
0$
b00 %
#2
b0010 #
#3
b0100 #
#4
b1000 #
#5
b0001 #
1$
#6
b0010 #
b01 %
#7
b0100 #
b10 %
#8
b1000 #
b11 %
#9
b1010 #
#10
b1100 #
