Learn_Chisel/Myexercise/ex8.5_1/verilog/vsrc/Top.v
module Timing(
  input  [3:0] io_in,
  output [7:0] io_seg
);
  wire [7:0] _GEN_0 = io_in == 4'hf ? 8'h71 : 8'hff; // @[Timing.scala 28:{36,45} 29:25]
  wire [7:0] _GEN_1 = io_in == 4'he ? 8'h61 : _GEN_0; // @[Timing.scala 27:{36,45}]
  wire [7:0] _GEN_2 = io_in == 4'hd ? 8'h85 : _GEN_1; // @[Timing.scala 26:{36,45}]
  wire [7:0] _GEN_3 = io_in == 4'hc ? 8'h63 : _GEN_2; // @[Timing.scala 25:{36,45}]
  wire [7:0] _GEN_4 = io_in == 4'hb ? 8'hc1 : _GEN_3; // @[Timing.scala 24:{36,45}]
  wire [7:0] _GEN_5 = io_in == 4'ha ? 8'h11 : _GEN_4; // @[Timing.scala 23:{36,45}]
  wire [7:0] _GEN_6 = io_in == 4'h9 ? 8'h9 : _GEN_5; // @[Timing.scala 22:{36,45}]
  wire [7:0] _GEN_7 = io_in == 4'h8 ? 8'h1 : _GEN_6; // @[Timing.scala 21:{36,45}]
  wire [7:0] _GEN_8 = io_in == 4'h7 ? 8'h1f : _GEN_7; // @[Timing.scala 20:{36,45}]
  wire [7:0] _GEN_9 = io_in == 4'h6 ? 8'h41 : _GEN_8; // @[Timing.scala 19:{36,45}]
  wire [7:0] _GEN_10 = io_in == 4'h5 ? 8'h49 : _GEN_9; // @[Timing.scala 18:{36,45}]
  wire [7:0] _GEN_11 = io_in == 4'h4 ? 8'h99 : _GEN_10; // @[Timing.scala 17:{36,45}]
  wire [7:0] _GEN_12 = io_in == 4'h3 ? 8'hd : _GEN_11; // @[Timing.scala 16:{36,45}]
  wire [7:0] _GEN_13 = io_in == 4'h2 ? 8'h25 : _GEN_12; // @[Timing.scala 15:{36,45}]
  wire [7:0] _GEN_14 = io_in == 4'h1 ? 8'h9f : _GEN_13; // @[Timing.scala 14:{36,45}]
  assign io_seg = io_in == 4'h0 ? 8'h3 : _GEN_14; // @[Timing.scala 13:{29,38}]
endmodule
module Top(
  input        clock,
  input        reset,
  output [7:0] io_seg
);
`ifdef RANDOMIZE_REG_INIT
  reg [31:0] _RAND_0;
  reg [31:0] _RAND_1;
`endif // RANDOMIZE_REG_INIT
  wire [3:0] timing_io_in; // @[Timing.scala 62:22]
  wire [7:0] timing_io_seg; // @[Timing.scala 62:22]
  reg [3:0] counter4; // @[Timing.scala 39:25]
  reg [26:0] secCounter; // @[Timing.scala 44:27]
  wire [25:0] _T_1 = 26'h2faf080 - 26'h1; // @[Timing.scala 49:34]
  wire [26:0] _GEN_3 = {{1'd0}, _T_1}; // @[Timing.scala 49:19]
  wire  tick = secCounter == _GEN_3; // @[Timing.scala 49:19]
  wire [26:0] _secCounter_T_1 = secCounter + 27'h1; // @[Timing.scala 53:30]
  wire [3:0] _counter4_T_1 = counter4 + 4'h1; // @[Timing.scala 58:26]
  Timing timing ( // @[Timing.scala 62:22]
    .io_in(timing_io_in),
    .io_seg(timing_io_seg)
  );
  assign io_seg = timing_io_seg; // @[Timing.scala 64:10]
  assign timing_io_in = counter4; // @[Timing.scala 63:16]
  always @(posedge clock) begin
    if (reset) begin // @[Timing.scala 39:25]
      counter4 <= 4'h0; // @[Timing.scala 39:25]
    end else if (tick) begin // @[Timing.scala 57:14]
      counter4 <= _counter4_T_1; // @[Timing.scala 58:14]
    end
    if (reset) begin // @[Timing.scala 44:27]
      secCounter <= 27'h0; // @[Timing.scala 44:27]
    end else if (tick) begin // @[Timing.scala 49:41]
      secCounter <= 27'h0; // @[Timing.scala 50:16]
    end else begin
      secCounter <= _secCounter_T_1; // @[Timing.scala 53:16]
    end
  end
// Register and memory initialization
`ifdef RANDOMIZE_GARBAGE_ASSIGN
`define RANDOMIZE
`endif
`ifdef RANDOMIZE_INVALID_ASSIGN
`define RANDOMIZE
`endif
`ifdef RANDOMIZE_REG_INIT
`define RANDOMIZE
`endif
`ifdef RANDOMIZE_MEM_INIT
`define RANDOMIZE
`endif
`ifndef RANDOM
`define RANDOM $random
`endif
`ifdef RANDOMIZE_MEM_INIT
  integer initvar;
`endif
`ifndef SYNTHESIS
`ifdef FIRRTL_BEFORE_INITIAL
`FIRRTL_BEFORE_INITIAL
`endif
initial begin
  `ifdef RANDOMIZE
    `ifdef INIT_RANDOM
      `INIT_RANDOM
    `endif
    `ifndef VERILATOR
      `ifdef RANDOMIZE_DELAY
        #`RANDOMIZE_DELAY begin end
      `else
        #0.002 begin end
      `endif
    `endif
`ifdef RANDOMIZE_REG_INIT
  _RAND_0 = {1{`RANDOM}};
  counter4 = _RAND_0[3:0];
  _RAND_1 = {1{`RANDOM}};
  secCounter = _RAND_1[26:0];
`endif // RANDOMIZE_REG_INIT
  `endif // RANDOMIZE
end // initial
`ifdef FIRRTL_AFTER_INITIAL
`FIRRTL_AFTER_INITIAL
`endif
`endif // SYNTHESIS
endmodule

Learn_Chisel/Myexercise/ex8.5_1/test_run_dir/Top_should_pass/Top.vcd
$date
2025-01-13T06:01+0000
$end
$version
0.2
$end
$comment

$end
$timescale 1ns  $end
$scope module Top $end
 $var wire 27 ! secCounter $end
 $var wire 1 # timing $end
 $var wire 1 $ tick $end
 $var wire 1 % clock $end
 $var wire 4 ' counter4 $end
 $var wire 1 ( reset $end
 $var wire 8 ) io_seg $end
  $scope module timing $end
   $var wire 4 " io_in $end
   $var wire 8 & io_seg $end
  $upscope $end
$upscope $end
$enddefinitions $end
$dumpvars
0%
b0000 '
0#
b00000000 )
b000000000000000000000000000 !
b00000000 &
b0000 "
0$
0(
$end
#0
b00000011 &
1(
b00000011 )
#1
1%
#6
0%
0(
#11
b000000000000000000000000001 !
1%
#16
0%
#21
b000000000000000000000000010 !
1%
#26
0%
#31
b000000000000000000000000011 !
1%
#36
0%
#41
b000000000000000000000000100 !
1%
#46
0%
#51
b000000000000000000000000101 !
1%
#56
0%
#61
b000000000000000000000000110 !
1%
#66
0%
#71
b000000000000000000000000111 !
1%
#76
0%
#81
b000000000000000000000001000 !
1%
#86
0%
#91
b000000000000000000000001001 !
1%
1$
#96
0%
#101
b000000000000000000000000000 !
1%
b0001 "
b10011111 &
b0001 '
0$
b10011111 )
#106
0%
#111
b000000000000000000000000001 !
1%
#116
0%
#121
b000000000000000000000000010 !
1%
#126
0%
#131
b000000000000000000000000011 !
1%
#136
0%
#141
b000000000000000000000000100 !
1%
#146
0%
#151
b000000000000000000000000101 !
1%
#156
0%
#161
b000000000000000000000000110 !
1%
#166
0%
#171
b000000000000000000000000111 !
1%
#176
0%
#181
b000000000000000000000001000 !
1%
#186
0%
#191
b000000000000000000000001001 !
1%
1$
#196
0%
#201
b000000000000000000000000000 !
1%
b0010 "
b00100101 &
b0010 '
0$
b00100101 )
#206
0%
#211
b000000000000000000000000001 !
1%
#216
0%
#221
b000000000000000000000000010 !
1%
#226
0%
#231
b000000000000000000000000011 !
1%
#236
0%
#241
b000000000000000000000000100 !
1%
#246
0%
#251
b000000000000000000000000101 !
1%
#256
0%
#261
b000000000000000000000000110 !
1%
#266
0%
#271
b000000000000000000000000111 !
1%
#276
0%
#281
b000000000000000000000001000 !
1%
#286
0%
#291
b000000000000000000000001001 !
1%
1$
#296
0%
#301
b000000000000000000000000000 !
1%
b0011 "
b00001101 &
b0011 '
0$
b00001101 )
#306
0%
#311
b000000000000000000000000001 !
1%
#316
0%
#321
b000000000000000000000000010 !
1%
#326
0%
#331
b000000000000000000000000011 !
1%
#336
0%
#341
b000000000000000000000000100 !
1%
#346
0%
#351
b000000000000000000000000101 !
1%
#356
0%
#361
b000000000000000000000000110 !
1%
#366
0%
#371
b000000000000000000000000111 !
1%
#376
0%
#381
b000000000000000000000001000 !
1%
#386
0%
#391
b000000000000000000000001001 !
1%
1$
#396
0%
#401
b000000000000000000000000000 !
1%
b0100 "
b10011001 &
b0100 '
0$
b10011001 )
#406
0%
#411
b000000000000000000000000001 !
1%
#416
0%
#421
b000000000000000000000000010 !
1%
#426
0%
#431
b000000000000000000000000011 !
1%
#436
0%
#441
b000000000000000000000000100 !
1%
#446
0%
#451
b000000000000000000000000101 !
1%
#456
0%
#461
b000000000000000000000000110 !
1%
#466
0%
#471
b000000000000000000000000111 !
1%
#476
0%
#481
b000000000000000000000001000 !
1%
#486
0%
#491
b000000000000000000000001001 !
1%
1$
#496
0%
#501
b000000000000000000000000000 !
1%
b0101 "
b01001001 &
b0101 '
0$
b01001001 )
#506
0%
#511
b000000000000000000000000001 !
1%
#516
0%
#521
b000000000000000000000000010 !
1%
#526
0%
#531
b000000000000000000000000011 !
1%
#536
0%
#541
b000000000000000000000000100 !
1%
#546
0%
#551
b000000000000000000000000101 !
1%
#556
0%
#561
b000000000000000000000000110 !
1%
#566
0%
#571
b000000000000000000000000111 !
1%
#576
0%
#581
b000000000000000000000001000 !
1%
#586
0%
#591
b000000000000000000000001001 !
1%
1$
#596
0%
#601
b000000000000000000000000000 !
1%
b0110 "
b01000001 &
b0110 '
0$
b01000001 )
#606
0%
#611
b000000000000000000000000001 !
1%
#616
0%
#621
b000000000000000000000000010 !
1%
#626
0%
#631
b000000000000000000000000011 !
1%
#636
0%
#641
b000000000000000000000000100 !
1%
#646
0%
#651
b000000000000000000000000101 !
1%
#656
0%
#661
b000000000000000000000000110 !
1%
#666
0%
#671
b000000000000000000000000111 !
1%
#676
0%
#681
b000000000000000000000001000 !
1%
#686
0%
#691
b000000000000000000000001001 !
1%
1$
#696
0%
#701
b000000000000000000000000000 !
1%
b0111 "
b00011111 &
b0111 '
0$
b00011111 )
#706
0%
#711
b000000000000000000000000001 !
1%
#716
0%
#721
b000000000000000000000000010 !
1%
#726
0%
#731
b000000000000000000000000011 !
1%
#736
0%
#741
b000000000000000000000000100 !
1%
#746
0%
#751
b000000000000000000000000101 !
1%
#756
0%
#761
b000000000000000000000000110 !
1%
#766
0%
#771
b000000000000000000000000111 !
1%
#776
0%
#781
b000000000000000000000001000 !
1%
#786
0%
#791
b000000000000000000000001001 !
1%
1$
#796
0%
#801
b000000000000000000000000000 !
1%
b1000 "
b00000001 &
b1000 '
0$
b00000001 )
#806
0%
#811
b000000000000000000000000001 !
1%
#816
0%
#821
b000000000000000000000000010 !
1%
#826
0%
#831
b000000000000000000000000011 !
1%
#836
0%
#841
b000000000000000000000000100 !
1%
#846
0%
#851
b000000000000000000000000101 !
1%
#856
0%
#861
b000000000000000000000000110 !
1%
#866
0%
#871
b000000000000000000000000111 !
1%
#876
0%
#881
b000000000000000000000001000 !
1%
#886
0%
#891
b000000000000000000000001001 !
1%
1$
#896
0%
#901
b000000000000000000000000000 !
1%
b1001 "
b00001001 &
b1001 '
0$
b00001001 )
#906
0%
#911
b000000000000000000000000001 !
1%
#916
0%
#921
b000000000000000000000000010 !
1%
#926
0%
#931
b000000000000000000000000011 !
1%
#936
0%
#941
b000000000000000000000000100 !
1%
#946
0%
#951
b000000000000000000000000101 !
1%
#956
0%
#961
b000000000000000000000000110 !
1%
#966
0%
#971
b000000000000000000000000111 !
1%
#976
0%
#981
b000000000000000000000001000 !
1%
#986
0%
#991
b000000000000000000000001001 !
1%
1$
#996
0%
#1001
b000000000000000000000000000 !
1%
b1010 "
b00010001 &
b1010 '
0$
b00010001 )
#1006
0%
#1011
b000000000000000000000000001 !
1%
#1016
0%
#1021
b000000000000000000000000010 !
1%
#1026
0%
#1031
b000000000000000000000000011 !
1%
#1036
0%
#1041
b000000000000000000000000100 !
1%
#1046
0%
#1051
b000000000000000000000000101 !
1%
#1056
0%
#1061
b000000000000000000000000110 !
1%
#1066
0%
#1071
b000000000000000000000000111 !
1%
#1076
0%
#1081
b000000000000000000000001000 !
1%
#1086
0%
#1091
b000000000000000000000001001 !
1%
1$
#1096
0%
#1101
b000000000000000000000000000 !
1%
b1011 "
b11000001 &
b1011 '
0$
b11000001 )
#1106
0%
#1111
b000000000000000000000000001 !
1%
#1116
0%
#1121
b000000000000000000000000010 !
1%
#1126
0%
#1131
b000000000000000000000000011 !
1%
#1136
0%
#1141
b000000000000000000000000100 !
1%
#1146
0%
#1151
b000000000000000000000000101 !
1%
#1156
0%
#1161
b000000000000000000000000110 !
1%
#1166
0%
#1171
b000000000000000000000000111 !
1%
#1176
0%
#1181
b000000000000000000000001000 !
1%
#1186
0%
#1191
b000000000000000000000001001 !
1%
1$
#1196
0%
#1201
b000000000000000000000000000 !
1%
b1100 "
b01100011 &
b1100 '
0$
b01100011 )
#1206
0%
#1211
b000000000000000000000000001 !
1%
#1216
0%
#1221
b000000000000000000000000010 !
1%
#1226
0%
#1231
b000000000000000000000000011 !
1%
#1236
0%
#1241
b000000000000000000000000100 !
1%
#1246
0%
#1251
b000000000000000000000000101 !
1%
#1256
0%
#1261
b000000000000000000000000110 !
1%
#1266
0%
#1271
b000000000000000000000000111 !
1%
#1276
0%
#1281
b000000000000000000000001000 !
1%
#1286
0%
#1291
b000000000000000000000001001 !
1%
1$
#1296
0%
#1301
b000000000000000000000000000 !
1%
b1101 "
b10000101 &
b1101 '
0$
b10000101 )
#1306
0%
#1311
b000000000000000000000000001 !
1%
#1316
0%
#1321
b000000000000000000000000010 !
1%
#1326
0%
#1331
b000000000000000000000000011 !
1%
#1336
0%
#1341
b000000000000000000000000100 !
1%
#1346
0%
#1351
b000000000000000000000000101 !
1%
#1356
0%
#1361
b000000000000000000000000110 !
1%
#1366
0%
#1371
b000000000000000000000000111 !
1%
#1376
0%
#1381
b000000000000000000000001000 !
1%
#1386
0%
#1391
b000000000000000000000001001 !
1%
1$
#1396
0%
#1401
b000000000000000000000000000 !
1%
b1110 "
b01100001 &
b1110 '
0$
b01100001 )
#1406
0%
#1411
b000000000000000000000000001 !
1%
#1416
0%
#1421
b000000000000000000000000010 !
1%
#1426
0%
#1431
b000000000000000000000000011 !
1%
#1436
0%
#1441
b000000000000000000000000100 !
1%
#1446
0%
#1451
b000000000000000000000000101 !
1%
#1456
0%
#1461
b000000000000000000000000110 !
1%
#1466
0%
#1471
b000000000000000000000000111 !
1%
#1476
0%
#1481
b000000000000000000000001000 !
1%
#1486
0%
#1491
b000000000000000000000001001 !
1%
1$
#1496
0%
#1501
b000000000000000000000000000 !
1%
b1111 "
b01110001 &
b1111 '
0$
b01110001 )
#1506
0%
#1511
b000000000000000000000000001 !
1%
